supotato
