Metadata-Version: 1.0
Name: supotato
Version: 2.0.4
Summary: Classify the header (.h) files in to a txt report.
Home-page: http://github.com/everettjf/supotato
Author: everettjf
Author-email: everettjf@live.com
License: MIT
Platform: UNKNOWN
